rokso/__init__.py
rokso/roksopsql.py
rokso/lib/__init__.py
rokso/lib/agent.py
rokso/lib/configManager.py
rokso/lib/connectionManager.py
rokso/lib/dbManager.py
rokso/lib/migrationManager.py
rokso/lib/remapHelper.py
rokso/lib/remappingSqls.py
roksopsql-0.2.4.dist-info/LICENSE.md
roksopsql-0.2.4.dist-info/METADATA
roksopsql-0.2.4.dist-info/WHEEL
roksopsql-0.2.4.dist-info/entry_points.txt
roksopsql-0.2.4.dist-info/top_level.txt
roksopsql-0.2.4.dist-info/RECORD
