Metadata-Version: 2.1
Name: roksopsql
Version: 0.2.4
Summary: Rokso migration package for PostgreSQL database migrations.
Home-page: https://github.com/matrixbegins/rokso-pgsql
Author: Ankur Pandey
Author-email: matrixbegins@gmail.com
License: MIT
Project-URL: Bug Tracker, https://github.com/matrixbegins/rokso-pgsql/issues
Keywords: Postgresql,database-migration,python-database-migration
Platform: UNKNOWN
Classifier: Programming Language :: Python :: 3
Classifier: License :: OSI Approved :: MIT License
Classifier: Development Status :: 3 - Alpha
Classifier: Operating System :: POSIX :: Linux
Classifier: Operating System :: MacOS
Classifier: Operating System :: MacOS :: MacOS X
Classifier: Topic :: Database
Classifier: Programming Language :: Python :: 3.8
Requires-Python: >=3.3
Requires-Dist: click (==7.1.1)
Requires-Dist: protobuf (==3.14.0)
Requires-Dist: psycopg2-binary (==2.8.6)
Requires-Dist: six (==1.15.0)
Requires-Dist: tabulate (==0.8.7)
Requires-Dist: colorama (==0.4.4)
